{"stat.leaveGame":3,"stat.mineBlock.minecraft.cobblestone":31,"stat.pickup.minecraft.flint":84,"stat.pickup.forestry.resources":18,"stat.swimOneCm":36530,"stat.useItem.minecraft.dirt":63,"stat.useItem.minecraft.stone_slab2":22,"stat.pickup.minecraft.rotten_flesh":5,"stat.craftItem.minecraft.furnace":1,"stat.craftItem.minecraft.stone_axe":2,"stat.mineBlock.zawa.dried_bamboo":1,"stat.pickup.biomesoplenty.pear":1,"stat.craftItem.minecraft.stone_pickaxe":4,"stat.pickup.minecraft.cobblestone":1328,"stat.useItem.minecraft.stone_shovel":474,"stat.craftItem.minecraft.stone_sword":1,"stat.flyOneCm":40619,"stat.pickup.minecraft.fish":2,"stat.pickup.minecraft.redstone":110,"stat.mineBlock.minecraft.iron_ore":10,"stat.timeSinceDeath":129866,"stat.useItem.biomesoplenty.pear":1,"stat.pickup.minecraft.mutton":5,"stat.pickup.zawa.temple_bells":2,"stat.pickup.zawa.sea_urchin_tropical":1,"stat.craftItem.minecraft.bed":1,"stat.furnaceInteraction":16,"stat.drop.minecraft.gravel":1,"stat.mineBlock.minecraft.coal_ore":68,"stat.craftItem.minecraft.stone_hoe":1,"stat.pickup.minecraft.string":4,"stat.mineBlock.zawa.kelp":1,"stat.pickup.minecraft.furnace":1,"stat.useItem.minecraft.cooked_mutton":5,"stat.craftItem.minecraft.stone_slab2":0,"stat.pickup.zawa.reptile_meat_raw":3,"stat.killEntity.Squid":3,"stat.sprintOneCm":85177,"stat.pickup.biomesoplenty.flower_0":1,"stat.mineBlock.biomesoplenty.flower_0":1,"stat.useItem.minecraft.stone_stairs":3,"stat.craftItem.minecraft.wooden_axe":1,"stat.craftItem.minecraft.stick":24,"stat.useItem.minecraft.wheat_seeds":20,"stat.mineBlock.minecraft.crafting_table":2,"stat.useItem.minecraft.wooden_shovel":59,"stat.pickup.zawa.gracilaria":1,"stat.mineBlock.zawa.gracilaria":1,"stat.drop":7,"stat.playOneMinute":129866,"stat.craftItem.minecraft.wooden_shovel":1,"stat.killEntity.Sheep":4,"stat.killEntity.Zombie":3,"stat.mineBlock.minecraft.tallgrass":102,"stat.craftItem.minecraft.cooked_mutton":5,"stat.diveOneCm":55952,"stat.chestOpened":44,"stat.useItem.minecraft.fish":2,"stat.useItem.minecraft.stone":16,"stat.pickup.minecraft.gravel":831,"stat.useItem.minecraft.apple":1,"stat.drop.minecraft.flint":1,"stat.craftItem.minecraft.coal":72,"stat.useItem.minecraft.rotten_flesh":5,"stat.jump":815,"stat.pickup.minecraft.coal":67,"stat.fallOneCm":9485,"stat.pickup.zawa.cockatoo_egg":3,"stat.useItem.minecraft.stone_axe":39,"stat.pickup.zawa.dried_bamboo_shoot":1,"stat.crouchOneCm":9510,"stat.mineBlock.minecraft.chest":2,"stat.pickup.minecraft.spider_eye":2,"stat.craftItem.minecraft.chest":5,"stat.craftItem.minecraft.torch":16,"stat.pickup.minecraft.dirt":577,"stat.craftingTableInteraction":29,"stat.pickup.minecraft.iron_ore":37,"stat.mineBlock.zawa.temple_bells":2,"stat.pickup.minecraft.wooden_pickaxe":1,"stat.damageTaken":420,"stat.mineBlock.minecraft.torch":4,"stat.useItem.minecraft.wooden_pickaxe":32,"stat.pickup.zawa.kelp":7,"stat.pickup.minecraft.log2":2,"stat.mineBlock.biomesoplenty.plant_0":108,"stat.pickup.minecraft.dye":4,"stat.pickup.minecraft.planks":6,"stat.pickup.minecraft.wheat_seeds":24,"stat.drop.zawa.kelp":5,"stat.mineBlock.minecraft.gravel":478,"stat.useItem.minecraft.stone_pickaxe":235,"stat.useItem.minecraft.stone_sword":82,"stat.damageDealt":1931,"stat.sleepInBed":6,"stat.mineBlock.minecraft.dirt":71,"stat.useItem.zawa.kelp":2,"stat.craftItem.minecraft.stone_shovel":4,"stat.walkOneCm":596561,"stat.useItem.minecraft.bread":3,"stat.useItem.minecraft.torch":2,"stat.mineBlock.biomesoplenty.leaves_2":8,"stat.useItem.minecraft.chest":3,"stat.pickup.minecraft.stick":23,"stat.useItem.zawa.reptile_meat_raw":2,"stat.craftItem.minecraft.stone_stairs":4,"stat.pickup.minecraft.crafting_table":3,"stat.useItem.minecraft.log":3,"stat.pickup.mekanism.oreblock":33,"stat.useItem.minecraft.cobblestone":15,"stat.pickup.biomesoplenty.sapling_1":12,"stat.craftItem.minecraft.crafting_table":1,"stat.useItem.minecraft.gravel":87,"stat.mineBlock.minecraft.double_plant":7,"stat.pickup.minecraft.log":581,"stat.pickup.minecraft.stone":159,"stat.mineBlock.zawa.bellflowers":2,"stat.pickup.zawa.bellflowers":1,"stat.pickup.minecraft.sapling":11,"stat.mineBlock.zawa.sea_urchin_tropical":1,"stat.pickup.minecraft.apple":1,"stat.pickup.biomesoplenty.gem":1,"stat.pickup.forestry.scoop":2,"stat.craftItem.minecraft.planks":164,"stat.killEntity.Spider":1,"stat.pickup.minecraft.bread":3,"stat.mineBlock.forestry.resources":12,"stat.mobKills":13,"stat.mineBlock.minecraft.log":44,"stat.craftItem.minecraft.wooden_door":3,"stat.useItem.minecraft.stone_hoe":50,"stat.pickup.forestry.book_forester":1,"stat.useItem.minecraft.wooden_door":1,"stat.pickup.minecraft.diamond":8,"stat.mineBlock.minecraft.leaves":3,"stat.pickup.minecraft.torch":9,"stat.sneakTime":3374,"stat.pickup.minecraft.wool":4,"stat.useItem.minecraft.wooden_axe":38,"stat.mineBlock.minecraft.stone":119,"stat.pickup.minecraft.chest":3}